fonts/OpenSans-Regular.ttf
wrdcld/__init__.py
wrdcld/font.py
wrdcld/image.py
wrdcld/main.py
wrdcld/rectangle.py
wrdcld/util.py
wrdcld-0.2.0.dist-info/LICENSE
wrdcld-0.2.0.dist-info/METADATA
wrdcld-0.2.0.dist-info/WHEEL
wrdcld-0.2.0.dist-info/RECORD
