Metadata-Version: 2.1
Name: wrdcld
Version: 0.2.0
Summary: A predictable, interpretable wordcloud library
License: GPLv3
Author: Jim Barrett
Author-email: jimbarrett27@gmail.com
Requires-Python: >=3.9,<4.0
Classifier: License :: Other/Proprietary License
Classifier: Programming Language :: Python :: 3
Classifier: Programming Language :: Python :: 3.9
Classifier: Programming Language :: Python :: 3.10
Classifier: Programming Language :: Python :: 3.11
Classifier: Programming Language :: Python :: 3.12
Requires-Dist: pillow (>=10.4.0,<11.0.0)
